{
  "project_info": {
    "project_number": "1069769184947",
    "firebase_url": "https://nghethuatamthuc-b2d80.firebaseio.com",
    "project_id": "nghethuatamthuc-b2d80",
    "storage_bucket": "nghethuatamthuc-b2d80.appspot.com"
  },
  "client": [
    {
      "client_info": {
        "mobilesdk_app_id": "1:1069769184947:android:3424ed7a2f9a1f75",
        "android_client_info": {
          "package_name": "com.example.nghethuatamthuc"
        }
      },
      "oauth_client": [
        {
          "client_id": "1069769184947-gr6chjfbkj3v85cdvqspg99t8toi0p8p.apps.googleusercontent.com",
          "client_type": 3
        }
      ],
      "api_key": [
        {
          "current_key": "AIzaSyCJe36PsDQgIIpVf3zxDHa-j1N8O1dbwDg"
        }
      ],
      "services": {
        "appinvite_service": {
          "other_platform_oauth_client": [
            {
              "client_id": "1069769184947-gr6chjfbkj3v85cdvqspg99t8toi0p8p.apps.googleusercontent.com",
              "client_type": 3
            }
          ]
        }
      }
    }
  ],
  "configuration_version": "1"
}